couchdb/__init__.py
couchdb/__main__.py
couchdb/client.py
couchdb/design.py
couchdb/http.py
couchdb/json.py
couchdb/loader.py
couchdb/mapping.py
couchdb/multipart.py
couchdb/util.py
couchdb/util2.py
couchdb/util3.py
couchdb/view.py
couchdb/tests/__init__.py
couchdb/tests/__main__.py
couchdb/tests/client.py
couchdb/tests/couch_tests.py
couchdb/tests/couchhttp.py
couchdb/tests/design.py
couchdb/tests/loader.py
couchdb/tests/mapping.py
couchdb/tests/multipart.py
couchdb/tests/package.py
couchdb/tests/testutil.py
couchdb/tests/tools.py
couchdb/tests/view.py
couchdb/tools/__init__.py
couchdb/tools/dump.py
couchdb/tools/load.py
couchdb/tools/replicate.py
CouchDB_Linkaform-1.2.3.dev0.dist-info/COPYING
CouchDB_Linkaform-1.2.3.dev0.dist-info/METADATA
CouchDB_Linkaform-1.2.3.dev0.dist-info/WHEEL
CouchDB_Linkaform-1.2.3.dev0.dist-info/entry_points.txt
CouchDB_Linkaform-1.2.3.dev0.dist-info/top_level.txt
CouchDB_Linkaform-1.2.3.dev0.dist-info/zip-safe
CouchDB_Linkaform-1.2.3.dev0.dist-info/RECORD
