Metadata-Version: 2.1
Name: CouchDB-Linkaform
Version: 1.2.3.dev0
Summary: Python library for working with CouchDB
Home-page: https://github.com/linkaform/couchdb-python
Author: Linkaform
Author-email: erick@linkaform.com
Maintainer: Erick
Maintainer-email: erick@linkaform.com
License: BSD
Platform: UNKNOWN
Classifier: Development Status :: 6 - Mature
Classifier: Intended Audience :: Developers
Classifier: License :: OSI Approved :: BSD License
Classifier: Operating System :: OS Independent
Classifier: Programming Language :: Python :: 2
Classifier: Programming Language :: Python :: 2.7
Classifier: Programming Language :: Python :: 3
Classifier: Programming Language :: Python :: 3.4
Classifier: Programming Language :: Python :: 3.5
Classifier: Topic :: Database :: Front-Ends
Classifier: Topic :: Software Development :: Libraries :: Python Modules
